README.md
setup.cfg
setup.py
flake_master/__init__.py
flake_master/common_types.py
flake_master/run.py
flake_master.egg-info/PKG-INFO
flake_master.egg-info/SOURCES.txt
flake_master.egg-info/dependency_links.txt
flake_master.egg-info/entry_points.txt
flake_master.egg-info/not-zip-safe
flake_master.egg-info/requires.txt
flake_master.egg-info/top_level.txt
flake_master/utils/__init__.py
flake_master/utils/preset_fetchers.py
flake_master/utils/presets.py
flake_master/utils/requirements.py