Metadata-Version: 2.1
Name: flake-master
Version: 0.0.1
Summary: flake_master is a manager for flake8 plugins and configuration.
Home-page: https://github.com/Melevir/flake_master
Author: Ilya Lebedev
Author-email: melevir@gmail.com
License: MIT
Keywords: flake8 plugins
Platform: UNKNOWN
Classifier: Environment :: Console
Classifier: Operating System :: OS Independent
Classifier: Topic :: Software Development :: Libraries :: Python Modules
Classifier: Topic :: Software Development :: Quality Assurance
Classifier: Programming Language :: Python
Classifier: Programming Language :: Python :: 3.7
Classifier: Programming Language :: Python :: 3.8
